am232x/__init__.py
am232x/__main__.py
am232x/am232x.py
am232x/constants.py
am232x/exceptions.py
pyam232x-1.0.1.dist-info/LICENSE
pyam232x-1.0.1.dist-info/METADATA
pyam232x-1.0.1.dist-info/WHEEL
pyam232x-1.0.1.dist-info/entry_points.txt
pyam232x-1.0.1.dist-info/top_level.txt
pyam232x-1.0.1.dist-info/RECORD
